{"time":"2024-06-12T09:31:21+00:00","data":[{"id":"66696aecc9317e85130386cf","date":"2024-06-12T09:31:21+00:00","long":-3.6868017119652,"lat":40.349285491181,"address":"Calle Leonor Gongora, 50","description":"Seis sacos pequeños","service":"Recogida de saco o contenedor de escombros","typology":"Tengo un problema con un elemento en la calle"},{"id":"66696aae0d82896e380d2ef1","date":"2024-06-12T09:30:19+00:00","long":-3.6852767011154,"lat":40.349226968167,"address":"Calle Metal, 30","description":"Tres sacos pequeños","service":"Recogida de saco o contenedor de escombros","typology":"Tengo un problema con un elemento en la calle"},{"id":"66696a3ac99712a4d2017c39","date":"2024-06-12T09:28:22+00:00","long":-3.6846190034828,"lat":40.341104601987,"address":"Calle Paterna, 47","description":"Una saca blanca de escombros sin marca sin nombre","service":"Recogida de saco o contenedor de escombros","typology":"Tengo un problema con un elemento en la calle"},{"id":"66696a243f5571008109a779","date":"2024-06-12T09:28:01+00:00","long":-3.6447207343116,"lat":40.426886810018,"address":"Calle Arriaga, 19","description":"Basura y enseres abandonados en la via publica","service":"Limpieza en vías públicas","typology":"Tengo un problema con un elemento en la calle","url":"https://sic-apipro.madrid.es/uploads/local/open010/66696a25ee695903914778.jpeg"},{"id":"66696a04263106a3ae02dc36","date":"2024-06-12T09:27:30+00:00","long":-3.7300849855882,"lat":40.429520972836,"address":"Avenida Valladolid, 6","description":"Imposible acceso por la acera a parada 6-2407 linea 46 de la  \n\n@EMTmadrid  \n\n@EMTincidencias  \n\n, en Avenida de Valladolid a la altura brigada de tráfico de personas con movilidad reducida en silla de ruedas.","service":"Mejora de accesibilidad","typology":"Quiero solicitar un elemento nuevo en la calle","url":"https://sic-apipro.madrid.es/uploads/local/open010/66696a052aad8563045956.jpg"},{"id":"666968bd6ddf8c27c704465b","date":"2024-06-12T09:22:02+00:00","long":-3.7025396,"lat":40.4024301,"address":"Calle Ercilla, 26","description":"Retirar unos 26 sacos de escombro","service":"Recogida de saco o contenedor de escombros","typology":"Tengo un problema con un elemento en la calle","url":"https://sic-apipro.madrid.es/uploads/local/open010/666968beb1184321635457.png"},{"id":"666967eb90e4f09b51097307","date":"2024-06-12T09:18:33+00:00","long":-3.7102608258919,"lat":40.419013812364,"address":"Cuesta Santo Domingo, 1","description":"plaga de mosquitos alrededor de los arboles","service":"Plagas","typology":"Tengo un problema con un elemento en la calle"},{"id":"666967a7a59c6ad51700abc5","date":"2024-06-12T09:17:24+00:00","long":-3.5600236058235,"lat":40.402791286581,"address":"Calle Concejal Victorino Granizo, 131","description":"Manchas insalubres en acera","service":"Limpieza en vías públicas","typology":"Tengo un problema con un elemento en la calle","url":"https://sic-apipro.madrid.es/uploads/local/open010/666967a8a9434526554030.png"},{"id":"6669659747dc4cee780bede5","date":"2024-06-12T09:08:37+00:00","long":-3.7494345009327,"lat":40.396790094694,"address":"Calle Cuart De Poblet, 97","description":"No existe ningún banco cuando antes sí que existian","service":"Nueva instalación.","typology":"Quiero solicitar un elemento nuevo en la calle"},{"id":"6669651e537d65bcd00f63f0","date":"2024-06-12T09:06:35+00:00","long":-3.6840858310461,"lat":40.398813871582,"address":"Calle Mendez Alvaro, 44 A","description":"Losetas sueltas en acera","service":"Desperfecto en acera","typology":"Tengo un problema con un elemento en la calle","url":"https://sic-apipro.madrid.es/uploads/local/open010/66696521073e0050041046.png"},{"id":"666964a4a1a28785f2089f9e","date":"2024-06-12T09:04:30+00:00","long":-3.7183486875055,"lat":40.385067293224,"address":"Avenida Oporto, 2","description":"Se solicita la resolución de un Aviso referente a un problema de Desperfecto en calzada ubicado en Avenida Oporto, 2.","service":"Desperfecto en calzada","typology":"Tengo un problema con un elemento en la calle","url":"https://sic-apipro.madrid.es/uploads/local/open010/666964a6835ff153504366.jpeg"},{"id":"666963bcc4e5ee51fd0ea8f1","date":"2024-06-12T09:00:43+00:00","long":-3.6735172010649,"lat":40.434841856365,"address":"Calle Alonso Heredia, 4","description":"1 cubo de 360l marrón  \n\nrestaurante las botas 3","service":"Nuevo cubo o contenedor","typology":"Tengo un problema con un elemento en la calle"},{"id":"666963b6c51aba6cc005fa3d","date":"2024-06-12T09:00:35+00:00","long":-3.6916077,"lat":40.377356,"address":"Calle San Mario, 55","description":"2 saquitos","service":"Recogida de saco o contenedor de escombros","typology":"Tengo un problema con un elemento en la calle"},{"id":"66696350a983dd00590c39e7","date":"2024-06-12T08:58:54+00:00","long":-3.7055021073924,"lat":40.430979912582,"address":"Calle San Bernardo, 101","description":"desaparecido 1 contenedor de 2 ruedas amarillo","service":"Nuevo cubo o contenedor","typology":"Tengo un problema con un elemento en la calle"},{"id":"6669634f8af5ddf80b0a922a","date":"2024-06-12T08:58:53+00:00","long":-3.6613202708097,"lat":40.438808675306,"address":"Avenida Brasilia, 13","description":"Abrieron una zanja, en la acera, en la dirección indicada, lleva abierto hace 2 meses, hay unas vallas y unas chapas amarillas para tapar la zanja, baldosines de la acera sueltos. Es muy peligroso, solicita su reparación.","service":"Desperfecto en acera","typology":"Tengo un problema con un elemento en la calle"},{"id":"66696341ed44f658a309dfcd","date":"2024-06-12T08:58:39+00:00","long":-3.6673971481415,"lat":40.487300634513,"address":"Avenida Manoteras, 22","description":"CAMBIO TAMAÑO DE CUBO","service":"Cambio de tamaño de cubo","typology":"Tengo un problema con un elemento en la calle"},{"id":"66696331a983dd00590c39d7","date":"2024-06-12T08:58:22+00:00","long":-3.693704391611,"lat":40.462862082783,"address":"Calle Infanta Mercedes, 90","description":"Solicitamos limpieza del punto de aportación","service":"Cubo o contenedor en mal estado","typology":"Tengo un problema con un elemento en la calle","url":"https://sic-apipro.madrid.es/uploads/local/open010/66696332c648e134701434.png"},{"id":"666962c90f015b45bf006363","date":"2024-06-12T08:56:39+00:00","long":-3.7083483707695,"lat":40.412813810712,"address":"Calle Grafal, 7","description":"cubos rotos","service":"Cubo o contenedor en mal estado","typology":"Tengo un problema con un elemento en la calle"},{"id":"66696285711f57436f095730","date":"2024-06-12T08:55:32+00:00","long":-3.6467187005931,"lat":40.475693103717,"address":"Calle Mar De Las Antillas, 10","description":"hay mucha suciedad ya que por ahi duermen indigentes y hacen sus cosas","service":"Limpieza en vías públicas","typology":"Tengo un problema con un elemento en la calle"},{"id":"6669627c8af5ddf80b0a921e","date":"2024-06-12T08:55:23+00:00","long":-3.6981871120223,"lat":40.50491585516,"address":"Avenida Monasterio De El Escorial, 55","description":"Domicilio particular","service":"Muebles particulares","typology":"Tengo un problema con un elemento en la calle"},{"id":"66696230146ea2e0cf0ed39f","date":"2024-06-12T08:54:07+00:00","long":-3.6434455782286,"lat":40.385683977489,"address":"Calle Gerardo Diego, 11","description":"CONSERVACION  \n\nREPOSICION DE AGLOMERADO EN UNION CON EL VADO MED. APROX. 4m2  \n\nTIPO A2","service":"Desperfecto en calzada","typology":"Tengo un problema con un elemento en la calle"},{"id":"666962137d33e7c9cb0a5b09","date":"2024-06-12T08:53:35+00:00","long":-3.6599905921029,"lat":40.369309129613,"address":"Calle Esteban Carros, 73","description":"La fuente está inactiva, tiene un tapón de plástico en lugar del pulsador. Gracias.","service":"Incidencias en fuentes de beber","typology":"Tengo un problema con un elemento en la calle","url":"https://sic-apipro.madrid.es/uploads/local/open010/66696215136a6010993208.jpeg"},{"id":"666960e2ff77ff78d40297fd","date":"2024-06-12T08:48:31+00:00","long":-3.699189350009,"lat":40.370887223786,"address":"Avenida Poblados, 175","description":"4 saquitos","service":"Recogida de saco o contenedor de escombros","typology":"Tengo un problema con un elemento en la calle"},{"id":"666960d9088071929605e18f","date":"2024-06-12T08:48:22+00:00","long":-3.6618516414636,"lat":40.390940508762,"address":"Calle Monte Calobro, 7","description":"Nos llama de un colegio para comunicar que desde hace tres dias tienen practicamente en la entrada del cole 3 bolsas grandes de basura . , las han dejado ahi. No saben mas.  \n\nSolictia retirada  \n\nDirecc . facilitada monte calobro 5","service":"Limpieza en vías públicas","typology":"Tengo un problema con un elemento en la calle"},{"id":"666960cf036e5f1f340135b7","date":"2024-06-12T08:48:11+00:00","long":-3.693704391611,"lat":40.462862082783,"address":"Calle Infanta Mercedes, 90","description":"Horquilla arrancada","service":"Horquillas delimitadoras","typology":"Tengo un problema con un elemento en la calle","url":"https://sic-apipro.madrid.es/uploads/local/open010/666960d0ec89a210604867.png"},{"id":"6669607f1a9587365d06f058","date":"2024-06-12T08:46:53+00:00","long":-3.7027321160181,"lat":40.483190313131,"address":"Calle Santiago De Compostela, 38","description":"televisión antigua","service":"Muebles particulares","typology":"Tengo un problema con un elemento en la calle"},{"id":"666960371b86a678e602981e","date":"2024-06-12T08:45:41+00:00","long":-3.6430853018746,"lat":40.427623231296,"address":"Calle Marcelino Roa Vazquez, 15","description":"SUCIEDAD EN TODA LA CALLE POR EXCREMENTOS DE ANIMALES Y ORINA. SIEMPRE HAY CUBOS DE BASURA EN LAS ACERAS NO TIENEN SUFICIENTE HIGIENE.","service":"Limpieza en vías públicas","typology":"Tengo un problema con un elemento en la calle"},{"id":"666960028be6c27e8302dbb9","date":"2024-06-12T08:44:49+00:00","long":-3.6431434607867,"lat":40.426402182208,"address":"Calle Pedro Antonio De Alarcon, 14","description":"SUCIEDAD EN TODA LA CALLE POR EXCREMENTOS DE ANIMALES Y ORINA. SIEMPRE HAY CUBOS DE BASURA EN LAS ACERAS NO TIENEN SUFICIENTE HIGIENE.","service":"Limpieza en vías públicas","typology":"Tengo un problema con un elemento en la calle"},{"id":"66695ff866ea1313fa055fcd","date":"2024-06-12T08:44:39+00:00","long":-3.6782159196894,"lat":40.421791829609,"address":"Calle O'donnell, 19","description":"Cubo desaparecido","service":"Nuevo cubo o contenedor","typology":"Tengo un problema con un elemento en la calle"},{"id":"66695fe1aee2ba39fb08da32","date":"2024-06-12T08:44:16+00:00","long":-3.6677699340275,"lat":40.488721894258,"address":"Calle Oña, 11","description":"Rama grande en la vía pública","service":"Limpieza en vías públicas","typology":"Tengo un problema con un elemento en la calle"},{"id":"66695f3423816e0abb087379","date":"2024-06-12T08:41:22+00:00","long":-3.6478579351116,"lat":40.38871342796,"address":"Calle Pedro Laborde, 17","description":"solicita cambio de farola","service":"Peticiones alumbrado","typology":"Quiero solicitar un elemento nuevo en la calle"},{"id":"66695ec6ed44f658a309df9b","date":"2024-06-12T08:39:32+00:00","long":-3.7097582246733,"lat":40.454467352662,"address":"Calle Leñeros, 31","description":"Cubo amarillo de comunidad sin tapa, solicita uno nuevo y la retirada del antiguo.","service":"Cubo o contenedor en mal estado","typology":"Tengo un problema con un elemento en la calle"},{"id":"66695e98cc441d5a8c01c9f4","date":"2024-06-12T08:38:47+00:00","long":-3.6844486524796,"lat":40.435876753215,"address":"Calle Lagasca, 117","description":"Nuevo cubo","service":"Nuevo cubo o contenedor","typology":"Tengo un problema con un elemento en la calle"},{"id":"66695e95036e5f1f3401359a","date":"2024-06-12T08:38:43+00:00","long":-3.6066966433095,"lat":40.399261147165,"address":"Calle Dehesa De Vicalvaro, 11","description":"Solicita 1 cubo marrón","service":"Nuevo cubo o contenedor","typology":"Tengo un problema con un elemento en la calle"},{"id":"66695e79753761622408cdb3","date":"2024-06-12T08:38:16+00:00","long":-3.7010207661494,"lat":40.535582958966,"address":"Camino Sotillo A Fuencarral, 9","description":"retirada bolsas basura y suciedad","service":"Limpieza en vías públicas","typology":"Tengo un problema con un elemento en la calle"},{"id":"66695e4f38efb19fe70cb2eb","date":"2024-06-12T08:37:34+00:00","long":-3.7668403094645,"lat":40.377017050697,"address":"Calle General Millan Astray, 32","description":"Pájaro.","service":"Animales muertos","typology":"Tengo un problema con un elemento en la calle"},{"id":"66695db6112a263c44017701","date":"2024-06-12T08:35:01+00:00","long":-3.6735954623136,"lat":40.398602489729,"address":"Calle Jativa, 6","description":"Gato en acera dentro de una bolsa junto a escombros.","service":"Animales muertos","typology":"Tengo un problema con un elemento en la calle"},{"id":"66695da10e378b96ab0cf568","date":"2024-06-12T08:34:39+00:00","long":-3.6250834386449,"lat":40.433861628902,"address":"Calle Rufino Gonzalez, 60","description":"1 cubo de tapa naranja (360l)","service":"Nuevo cubo o contenedor","typology":"Tengo un problema con un elemento en la calle"},{"id":"66695d7a26b9edf17801312b","date":"2024-06-12T08:34:01+00:00","long":-3.6135211663811,"lat":40.444644318177,"address":"Calle Boltaña, 18","description":"CUBO","service":"Nuevo cubo o contenedor","typology":"Tengo un problema con un elemento en la calle"},{"id":"66695d5cc013175c6408d765","date":"2024-06-12T08:33:30+00:00","long":-3.7058251221755,"lat":40.41948692468,"address":"Calle Preciados, 25","description":"Solicita 1 cubo por desaparición","service":"Nuevo cubo o contenedor","typology":"Tengo un problema con un elemento en la calle"},{"id":"66695cdfaa433174b500e6ec","date":"2024-06-12T08:31:25+00:00","long":-3.6658203856162,"lat":40.413539515603,"address":"Calle Pez Austral, 3","description":"cubo amarillo comunidad","service":"Nuevo cubo o contenedor","typology":"Tengo un problema con un elemento en la calle"},{"id":"66695cdc29041d8b650cea79","date":"2024-06-12T08:31:21+00:00","long":-3.6289556,"lat":40.3838458,"address":"Calle Bruno Abundez, 46","description":"Gran cantidad de pequeños sacos de escombros así como dos sacas sin marca llenas de escombros restos de obras y otros elementos amontonados entre los contenedores de recogida de residuos y sobre la estrecha acera imposibilitan absolutamente el paso y entorpeciendo enormemente el normal vaciado de los contenedores. Calle Bruno Abundez frente 46-48. \"Instituto Tecnológico de Telefonica\"","service":"Recogida de saco o contenedor de escombros","typology":"Tengo un problema con un elemento en la calle","url":"https://sic-apipro.madrid.es/uploads/local/open010/66695cdfa82c8473936352.png"},{"id":"66695cc738efb19fe70cb2bc","date":"2024-06-12T08:31:01+00:00","long":-3.7717179361531,"lat":40.397723471683,"address":"Calle Galicia, 9","description":"REITADA DE UN COLCHON. LLAMA A CUALQUIER HORA GRACIAS","service":"Muebles particulares","typology":"Tengo un problema con un elemento en la calle"},{"id":"66695cad108fdec8ef0e8fb8","date":"2024-06-12T08:30:35+00:00","long":-3.6771284233909,"lat":40.403230537158,"address":"Calle Abtao, 3","description":"solicita 2 cubos de tapa amarilla porque le han desaparecido","service":"Nuevo cubo o contenedor","typology":"Tengo un problema con un elemento en la calle"},{"id":"66695c88fd11a31c09017a2f","date":"2024-06-12T08:29:57+00:00","long":-3.6660441018814,"lat":40.423939176304,"address":"Calle Los Peñascales, 14","description":"La calle peñascales en general siempre tiene un estado de suciedad lamentable. como muestra este vómito al lado de un coche y un animal muerto en la calzada. Es una calle de bastante transito peatonal pues es la salida natural de varios colegios y guarderías cercanos hacia doctor esquerdo y el metro. Dudo que se limpie todos los dias.","service":"Limpieza en vías públicas","typology":"Tengo un problema con un elemento en la calle"},{"id":"66695c6b8af5ddf80b0a91a7","date":"2024-06-12T08:29:29+00:00","long":-3.6665447325804,"lat":40.475440761239,"address":"Avenida San Luis, 140","description":"2 tapas de registro en la calzada mal ajustadas por lo que suenan muchpo cuando pasan los vehículos","service":"Alcantarillado","typology":"Tengo un problema con un elemento en la calle"},{"id":"66695c09753761622408cd9c","date":"2024-06-12T08:27:51+00:00","long":-3.684105683267,"lat":40.434004907026,"address":"Calle Maldonado, 13","description":"animal muerto","service":"Animales muertos","typology":"Tengo un problema con un elemento en la calle"},{"id":"66695bd5bec00d2fe3024f57","date":"2024-06-12T08:27:00+00:00","long":-3.6968720671345,"lat":40.504468842913,"address":"Avenida Monasterio De Silos, 57","description":"LLAMA PARA INFORMAR HAY 3 VAYAS DE OBRAS ABANDONADAS DESDE MESES, ESTÁN TUMBADAS EN LA ACERA, ELLA CASI SE CAE HACE POCO, SOLICITA QUE PASEN A RETIRARLAS.","service":"Muebles abandonados en vía pública","typology":"Tengo un problema con un elemento en la calle"},{"id":"66695bcd13fbe31ee10e7c7e","date":"2024-06-12T08:26:51+00:00","long":-3.6660441018814,"lat":40.423939176304,"address":"Calle Los Peñascales, 14","description":"Hay un animal muerto en mitad de la calzada","service":"Animales muertos","typology":"Tengo un problema con un elemento en la calle"},{"id":"66695b4ebdc9602af606280a","date":"2024-06-12T08:24:45+00:00","long":-3.7212196232687,"lat":40.48928357673,"address":"Calle Collado Del Mostajo, 17","description":"Solicita la limpieza porque nos se hace desde hace mucho tiempo","service":"Limpieza en vías públicas","typology":"Tengo un problema con un elemento en la calle"},{"id":"66695b3d1d90b8616808c97d","date":"2024-06-12T08:24:27+00:00","long":-3.7609708072352,"lat":40.397817223132,"address":"Calle Escalona, 25","description":"Solicita recogida de 6 cajas con enseres. Gracias.","service":"Muebles particulares","typology":"Tengo un problema con un elemento en la calle"},{"id":"66695b05d7ff3ebb65081429","date":"2024-06-12T08:23:31+00:00","long":-3.6793095328725,"lat":40.392258198556,"address":"Calle Planeta Tierra, 4","description":"Bar El Virrey de San Telmo  \n\nDesaparecido cubo de tapa naranja grande","service":"Nuevo cubo o contenedor","typology":"Tengo un problema con un elemento en la calle"},{"id":"66695aca0f107f0e4e0e48ce","date":"2024-06-12T08:22:32+00:00","long":-3.7148592326169,"lat":40.433147658121,"address":"Calle Melendez Valdes, 52","description":"se le ha caido unas llaves en un llavero como una mininavaja  en la alcantarilla","service":"Alcantarillado","typology":"Tengo un problema con un elemento en la calle"},{"id":"66695ac2943149a6a90effc7","date":"2024-06-12T08:22:24+00:00","long":-3.6884170570327,"lat":40.420663965996,"address":"Plaza Independencia, 5","description":"Comunidad propietarios por desaparición 1 cubo de restos de 120l","service":"Nuevo cubo o contenedor","typology":"Tengo un problema con un elemento en la calle"},{"id":"66695a8b86e7884b730c2dfc","date":"2024-06-12T08:21:29+00:00","long":-3.693749453035,"lat":40.404334716211,"address":"Paseo Delicias, 32","description":"GIMNASIO SOLICITA CUBO TAPA MARRON MEDIANO POR DESAPARICION","service":"Nuevo cubo o contenedor","typology":"Tengo un problema con un elemento en la calle"},{"id":"66695a820e378b96ab0cf547","date":"2024-06-12T08:21:21+00:00","long":-3.6962093574783,"lat":40.469504649797,"address":"Avenida Asturias, 41","description":"El día 08/06/2024 autorizó estacionamiento con tarjeta desde las 10:05 h hasta las 12:00 h aproximadamente. El parquímetro dio error de impresión y le hicieron el cargo en el banco por un importe de 0.65 cts €, por lo que dió por buena la autorización. Cuando volvió le habían puesto una multa a las 11:10 h. Al comprobar el banco después del cargo efectuaron le rechazaron el pago. Solicita comprobación, ya que cuando se marcho el pago de la autorización fue correcto y luego el parquímetro lo rechazó anulando el cargo en el banco","service":"Aviso de denuncia","typology":"Tengo un problema con un elemento en la calle"},{"id":"66695a7a59117427170b0a77","date":"2024-06-12T08:21:11+00:00","long":-3.6788630122181,"lat":40.405143802341,"address":"Calle Narciso Serra, 11","description":"SE SOLICITA CUBO POR NO HABER ENTRAGADO AVISOS ANTERIOS QUE APARECEN COMO CERRADOS","service":"Nuevo cubo o contenedor","typology":"Tengo un problema con un elemento en la calle"},{"id":"66695a54dff7b51a400d259b","date":"2024-06-12T08:20:34+00:00","long":-3.6520149093121,"lat":40.485940212384,"address":"Calle Pintor Ignacio De Zuloaga, 1","description":"El paso de peatones está roto en escuela infantil y los carrito de bebé se quedan pillados con riesgo de accidente","service":"Desperfecto en acera","typology":"Tengo un problema con un elemento en la calle","url":"https://sic-apipro.madrid.es/uploads/local/open010/66695a56c20a2862268103.png"},{"id":"66695a4c3b7eae57c70624ab","date":"2024-06-12T08:20:26+00:00","long":-3.680276435482,"lat":40.44501399679,"address":"Calle Duran, 5","description":"Nuevo cubo gris de tapa naranja para comunidad de vecinos, se lo ha tragado el camión. Calle duran 3-5-7.  \n\n8291224 (no atendido) Horario de conserje 9 a 13.30 y tarde de 17 a 20h","service":"Nuevo cubo o contenedor","typology":"Tengo un problema con un elemento en la calle"},{"id":"66695a36a84fd429b90079a9","date":"2024-06-12T08:20:03+00:00","long":-3.6996412,"lat":40.3689504,"address":"Calle Durcal, 14","description":"10 saquitos","service":"Recogida de saco o contenedor de escombros","typology":"Tengo un problema con un elemento en la calle"},{"id":"66695a0668d619b7a7028ebe","date":"2024-06-12T08:19:16+00:00","long":-3.7202902883291,"lat":40.409679844158,"address":"Calle Pizarra, 3","description":"Sofa abandonado","service":"Muebles abandonados en vía pública","typology":"Tengo un problema con un elemento en la calle"},{"id":"666959f0d59db0a0a90b28bf","date":"2024-06-12T08:18:53+00:00","long":-3.6643053,"lat":40.3978292,"address":"Calle Doctor Salgado, 16","description":"Nevera","service":"Muebles abandonados en vía pública","typology":"Tengo un problema con un elemento en la calle","url":"https://sic-apipro.madrid.es/uploads/local/open010/666959f5a084b890313361.png"},{"id":"666959ed8487d6cf490cca29","date":"2024-06-12T08:18:51+00:00","long":-3.6521295737475,"lat":40.485916156322,"address":"Calle Pintor Ignacio De Zuloaga, 2","description":"Agujero paso peatones en ambos lados","service":"Desperfecto en calzada","typology":"Tengo un problema con un elemento en la calle","url":"https://sic-apipro.madrid.es/uploads/local/open010/666959f235bbf307322662.png"},{"id":"666959b20fb525cb0100d636","date":"2024-06-12T08:17:53+00:00","long":-3.6742038854896,"lat":40.44048650879,"address":"Calle Cartagena, 116","description":"Solicita limpieza","service":"Limpieza en vías públicas","typology":"Tengo un problema con un elemento en la calle","url":"https://sic-apipro.madrid.es/uploads/local/open010/666959b3025c7070422330.jpg"},{"id":"6669598f649614963405a34e","date":"2024-06-12T08:17:17+00:00","long":-3.6531696,"lat":40.486178,"address":"Calle Infanta Catalina Micaela, 23","description":"Esta roto en escuela infantil y se quedan pillados los carros con riesgo de que los bebes se caigan","service":"Desperfecto en acera","typology":"Tengo un problema con un elemento en la calle","url":"https://sic-apipro.madrid.es/uploads/local/open010/666959962b80d113451174.png"},{"id":"666959830bf175fa670ed860","date":"2024-06-12T08:17:03+00:00","long":-3.7349316666667,"lat":40.390835,"address":"Calle Tortola, 10","description":"Nuevo contenedor iglú papel-cartón","service":"Nuevo cubo o contenedor","typology":"Tengo un problema con un elemento en la calle","url":"https://sic-apipro.madrid.es/uploads/local/open010/66695984a9448190949422.png"},{"id":"666959707429e849750603bd","date":"2024-06-12T08:16:47+00:00","long":-3.6942348494028,"lat":40.387628973231,"address":"Calle Julian Rabanedo, 21","description":"SILLAS","service":"Muebles abandonados en vía pública","typology":"Tengo un problema con un elemento en la calle"},{"id":"666959600fb525cb0100d62e","date":"2024-06-12T08:16:30+00:00","long":-3.5709907195547,"lat":40.441285626299,"address":"Calle Almanaque, 5","description":"3 Bolsas grandes con ropa usada, neumaticos de coche dañados, un mueble pequeño de acrilico abandonadas en la parte trasera de la calle indicada, la basura esta en la esquina de Calle de Agosto y Calle Otoño.","service":"Muebles abandonados en vía pública","typology":"Tengo un problema con un elemento en la calle","url":"https://sic-apipro.madrid.es/uploads/local/open010/6669596111e34841367297.jpg"},{"id":"6669595a7429e849750603b5","date":"2024-06-12T08:16:25+00:00","long":-3.6414510425342,"lat":40.463114323357,"address":"Calle Alcorisa, 13","description":"Adoquines levantados desde el número 13 al 19, riesgo de caída.","service":"Desperfecto en acera","typology":"Tengo un problema con un elemento en la calle"},{"id":"66695921925cb044720a6a50","date":"2024-06-12T08:15:27+00:00","long":-3.6969282555799,"lat":40.424883256043,"address":"Calle Pelayo, 59","description":"COMUNIDAD DE PROPIETARIOS SOLICITA 1 CUBO TAPA NARANJA MEDIANO DE 240L DOS RUEDAS. DESAPARECIDO","service":"Nuevo cubo o contenedor","typology":"Tengo un problema con un elemento en la calle"},{"id":"666958ed3b7eae57c706247e","date":"2024-06-12T08:14:33+00:00","long":-3.7348674237728,"lat":40.390873402874,"address":"Calle Tortola, 10","description":"Nuevo contenedor carga lateral fracción resto","service":"Nuevo cubo o contenedor","typology":"Tengo un problema con un elemento en la calle","url":"https://sic-apipro.madrid.es/uploads/local/open010/666958f0040b4162852946.png"},{"id":"666958e41d90b8616808c967","date":"2024-06-12T08:14:25+00:00","long":-3.7036387994885,"lat":40.380325178218,"address":"Calle Cristo De La Victoria, 49","description":"Basura por todos lados , no limpian ya ni las calles principales","service":"Limpieza en vías públicas","typology":"Tengo un problema con un elemento en la calle","url":"https://sic-apipro.madrid.es/uploads/local/open010/666958e5f156b005488840.png"},{"id":"666958cb9ae6ce6ebc04a08a","date":"2024-06-12T08:14:00+00:00","long":-3.6405668898087,"lat":40.444362479769,"address":"Calle Goitia, 9","description":"LLAMA PARA SOLICITAR 2 CUBOS: \n\n1 ORGÁNICO (MARRÓN) 2 RUEDAS  \n\n1 RESTOS (GRIS TAPA NARANJA) 2 RUEDAS","service":"Nuevo cubo o contenedor","typology":"Tengo un problema con un elemento en la calle"},{"id":"6669588dd0b76108b8018d08","date":"2024-06-12T08:13:00+00:00","long":-3.6890387860964,"lat":40.508461716757,"address":"Calle Caballero De Los Espejos, 30","description":"Muebles tirados en vía pública","service":"Muebles abandonados en vía pública","typology":"Tengo un problema con un elemento en la calle"},{"id":"666958657390845c8703534c","date":"2024-06-12T08:12:19+00:00","long":-3.6813352534183,"lat":40.428687924156,"address":"Calle Castello, 63","description":"Solicitan 1 cubo marrón y 1 cubo naranja, grandes","service":"Nuevo cubo o contenedor","typology":"Tengo un problema con un elemento en la calle"},{"id":"666958626b0934a272051a2b","date":"2024-06-12T08:12:16+00:00","long":-3.7043103575706,"lat":40.379940288991,"address":"Calle Cristo De La Victoria, 111","description":"Lleno de basura","service":"Limpieza en vías públicas","typology":"Tengo un problema con un elemento en la calle","url":"https://sic-apipro.madrid.es/uploads/local/open010/66695864c344f669092327.png"},{"id":"66695822697ea7aea3006487","date":"2024-06-12T08:11:12+00:00","long":-3.6476153077481,"lat":40.469467319463,"address":"Calle Pablo Serrano, 19","description":"frente a ese numero esta apagada una farola en las noches","service":"Farola apagada","typology":"Tengo un problema con un elemento en la calle"},{"id":"66695812d0b76108b8018cff","date":"2024-06-12T08:10:57+00:00","long":-3.6731697784241,"lat":40.464249260067,"address":"Calle Madre De Dios, 34","description":"Nuevo cubo","service":"Nuevo cubo o contenedor","typology":"Tengo un problema con un elemento en la calle"},{"id":"66695801c001ed4f0c0866a7","date":"2024-06-12T08:10:38+00:00","long":-3.7045916542411,"lat":40.379823059519,"address":"Calle Cristo De La Victoria, 113","description":"Lleno de basura, no limpian ni las calles principales","service":"Limpieza en vías públicas","typology":"Tengo un problema con un elemento en la calle","url":"https://sic-apipro.madrid.es/uploads/local/open010/6669580463040153482532.png"},{"id":"666957eb42ded9d0aa023f61","date":"2024-06-12T08:10:17+00:00","long":-3.6928501496841,"lat":40.43741229263,"address":"Calle Zurbano, 82","description":"cubo","service":"Nuevo cubo o contenedor","typology":"Tengo un problema con un elemento en la calle"},{"id":"666957dac368f7f09e0b3b78","date":"2024-06-12T08:10:01+00:00","long":-3.6962232713771,"lat":40.421072177257,"address":"Calle San Marcos, 42","description":"c/San Marcos 42. Solicito mantenimiento de la calzada. Se está levantando desde hace meses. En general en toda la calla. Por ejemplo, en San Marcos con San Bartolomé está hundida.","service":"Desperfecto en calzada","typology":"Tengo un problema con un elemento en la calle","url":"https://sic-apipro.madrid.es/uploads/local/open010/666957db6195c011066151.jpg"},{"id":"666957b7c78a272cbb0e5271","date":"2024-06-12T08:09:23+00:00","long":-3.705605306575,"lat":40.455938719472,"address":"Calle Jeronima Llorente, 8","description":"En el número 4, La pegatina de frecuencia de recogida está incorrecta, indica 14 cuando debería ser 7. En el numero 8 no hay pegatina.","service":"Cubo o contenedor en mal estado","typology":"Tengo un problema con un elemento en la calle","url":"https://sic-apipro.madrid.es/uploads/local/open010/666957b9204f4476107961.png"},{"id":"6669578878f64d7d440687f1","date":"2024-06-12T08:08:39+00:00","long":-3.6287005134423,"lat":40.42939605277,"address":"Calle Cangas De Onis, 24","description":"La tapa de la alcantarilla hace ruido al pasar los vehiculos","service":"Alcantarillado","typology":"Tengo un problema con un elemento en la calle"},{"id":"666956e12a51c81b890a5358","date":"2024-06-12T08:05:51+00:00","long":-3.6957040170037,"lat":40.413507705933,"address":"Calle Jesus, 2","description":"Cartones tirados fuera del contenedor","service":"Vaciado de cubo o contenedor","typology":"Tengo un problema con un elemento en la calle","url":"https://sic-apipro.madrid.es/uploads/local/open010/666956e3a2985519956008.png"},{"id":"666956df8c36bd99260f389d","date":"2024-06-12T08:05:48+00:00","long":-3.6077745494529,"lat":40.403287057493,"address":"Calle Velilla, 5","description":"Envié un aviso sobre limpieza pero no ha sido atendido.  \n\nTras realizar obras de alumbrado público, se quedó la calle llena de polvo.  \n\nRuego baldeo de calzada a esta altura.","service":"Limpieza en vías públicas","typology":"Tengo un problema con un elemento en la calle"},{"id":"666956d5ae3efe13430782a1","date":"2024-06-12T08:05:38+00:00","long":-3.7052836641669,"lat":40.456236082113,"address":"Calle Jeronima Llorente, 4 A","description":"Cambiar un contenedor de vidrio a tipo vacri","service":"Nuevo cubo o contenedor","typology":"Tengo un problema con un elemento en la calle","url":"https://sic-apipro.madrid.es/uploads/local/open010/666956d734d0e186892579.png"},{"id":"666956bf6a91be037d0d727b","date":"2024-06-12T08:05:17+00:00","long":-3.6529832705855,"lat":40.484756673378,"address":"Calle Pintor Antonio Saura, 3","description":"Han arreglado solo un lado de la acera en el número 6","service":"Desperfecto en acera","typology":"Tengo un problema con un elemento en la calle","url":"https://sic-apipro.madrid.es/uploads/local/open010/666956c20a95b245477744.png"},{"id":"6669567f649614963405a328","date":"2024-06-12T08:04:14+00:00","long":-3.6722436972036,"lat":40.381641729607,"address":"Calle Sierra De Contraviesa, 63","description":"una cama nido y dos colchones","service":"Muebles particulares","typology":"Tengo un problema con un elemento en la calle"},{"id":"6669567e0533fe3e940b1442","date":"2024-06-12T08:04:12+00:00","long":-3.6981347469774,"lat":40.424673273554,"address":"Calle Hortaleza, 65","description":"Entrega cubo","service":"Nuevo cubo o contenedor","typology":"Tengo un problema con un elemento en la calle"},{"id":"6669563bbc2ae6ec830e40c1","date":"2024-06-12T08:03:04+00:00","long":-3.6645304130095,"lat":40.399105397069,"address":"Calle Pico Cejo, 38","description":"Hola, buenos días,\n\nLlevamos 2 días con este punto en condiciones pésimas.\n\nParece un vertedero.\n\nPasen por favor a solucionar el problema cuanto antes.\n\nGracias.\nUn saludo.","service":"Limpieza en vías públicas","typology":"Tengo un problema con un elemento en la calle","url":"https://sic-apipro.madrid.es/uploads/local/open010/666962aa9c2e5199673248.jpg"},{"id":"6669562bac98c354960ccabf","date":"2024-06-12T08:02:50+00:00","long":-3.6766200467088,"lat":40.347931065392,"address":"Calle Bario, 3","description":"No hay alumbrado en la calle. Pide que se ponga alguna farola.","service":"Peticiones alumbrado","typology":"Quiero solicitar un elemento nuevo en la calle"},{"id":"666955ca1b2392858505a5b5","date":"2024-06-12T08:01:12+00:00","long":-3.7639633501828,"lat":40.391288446098,"address":"Calle Tembleque, 99","description":"Baldosa hundida","service":"Desperfecto en acera","typology":"Tengo un problema con un elemento en la calle"},{"id":"666955bcc368f7f09e0b3b62","date":"2024-06-12T08:00:58+00:00","long":-3.7003833194557,"lat":40.432452480324,"address":"Calle Raimundo Lulio, 2","description":"Nuevo cubo","service":"Nuevo cubo o contenedor","typology":"Tengo un problema con un elemento en la calle"},{"id":"6669559e8c36bd99260f3891","date":"2024-06-12T08:00:27+00:00","long":-3.6643335362854,"lat":40.44989950996,"address":"Calle Padre Claret, 20","description":"Ha pagado 1 euro con tarjeta y no le ha validado , pero si se lo ha cobrado","service":"No imprime tique o no valida PIN","typology":"Tengo un problema con un elemento en la calle"},{"id":"6669558cc78a272cbb0e525a","date":"2024-06-12T08:00:11+00:00","long":-3.6633478638617,"lat":40.396256307609,"address":"Calle Puerto De Canfranc, 10","description":"Un canape desmontado.","service":"Muebles particulares","typology":"Tengo un problema con un elemento en la calle"},{"id":"66695573ae3efe1343078290","date":"2024-06-12T07:59:45+00:00","long":-3.6948865648311,"lat":40.40356662193,"address":"Calle Pedro Unanue, 14","description":"excremento de perro","service":"Limpieza en vías públicas","typology":"Tengo un problema con un elemento en la calle"},{"id":"66695565c368f7f09e0b3b5b","date":"2024-06-12T07:59:30+00:00","long":-3.6983661947014,"lat":40.439252975773,"address":"Calle Vargas, 14","description":"Reparación de rueda","service":"Cubo o contenedor en mal estado","typology":"Tengo un problema con un elemento en la calle"},{"id":"6669550219e1dcb901069718","date":"2024-06-12T07:57:52+00:00","long":-3.6568890434735,"lat":40.500829199337,"address":"Avenida Isabel De Valois, 90","description":"Ciudadano solicita la poda de un solar. La maleza esta bastante crecida solicita que lo poden cuanto antes. Está al lado del Colegio Cortes de Cadiz","service":"Limpieza en solares municipales","typology":"Tengo un problema con un elemento en la calle"},{"id":"666954f24689f1e1bb0ea5c6","date":"2024-06-12T07:57:35+00:00","long":-3.6806048462244,"lat":40.355371766277,"address":"Avenida Los Rosales, 103","description":"1 SOFA ABANDONADO","service":"Muebles abandonados en vía pública","typology":"Tengo un problema con un elemento en la calle"},{"id":"666954aea971c7015d06a8d9","date":"2024-06-12T07:56:28+00:00","long":-3.6503798514605,"lat":40.429319671238,"address":"Calle Servando Batanero, 1 C","description":"Boquete en la acera","service":"Desperfecto en acera","typology":"Tengo un problema con un elemento en la calle"}]}